linkfy/__init__.py
linkfy/sub.py
linkfy-0.1.1.dist-info/DESCRIPTION.rst
linkfy-0.1.1.dist-info/METADATA
linkfy-0.1.1.dist-info/RECORD
linkfy-0.1.1.dist-info/WHEEL
linkfy-0.1.1.dist-info/metadata.json
linkfy-0.1.1.dist-info/top_level.txt
