Metadata-Version: 2.0
Name: linkfy
Version: 0.1.1
Summary: Change plain text into HTML.
Home-page: https://github.com/admire93/linky
Author: Kang Hyojun
Author-email: iam.kanghyojun@gmail.com
License: UNKNOWN
Platform: UNKNOWN
Classifier: Intended Audience :: Developers
Classifier: Programming Language :: Python :: 2
Classifier: Programming Language :: Python :: 2.7
Classifier: Programming Language :: Python :: 3
Classifier: Programming Language :: Python :: 3.3
Classifier: Programming Language :: Python :: 3.4
Classifier: Programming Language :: Python :: 3.5
Classifier: Topic :: Software Development :: Libraries :: Python Modules
Classifier: Topic :: Software Development :: Quality Assurance
Requires-Dist: MarkupSafe (>=0.23)
Provides-Extra: dev
Requires-Dist: flake8; extra == 'dev'
Requires-Dist: import-order; extra == 'dev'
Provides-Extra: tests
Requires-Dist: pytest (>=2.7.0); extra == 'tests'
Requires-Dist: pytest-xdist; extra == 'tests'
Requires-Dist: tox; extra == 'tests'
